messi_add_method/__init__.py
messi_add_method/create_method.py
messi_add_method-1.0.0.dist-info/METADATA
messi_add_method-1.0.0.dist-info/WHEEL
messi_add_method-1.0.0.dist-info/top_level.txt
messi_add_method-1.0.0.dist-info/RECORD
